{
	"allowed_clients": [],
	"allowed_logout_urls": [
		"https://##ENV##.myapp.com/logout"
	],
	"allowed_origins": [
		"https://##ENV##.myapp.com/"
	],
	"app_type": "spa",
	"callback_url_template": false,
	"callbacks": [
		"https://##ENV##.myapp.com/callback"
	],
	"cross_origin_auth": false,
	"custom_login_page_on": true,
	"description": "My SPA Application",
	"global": false,
	"grant_types": [
		"authorization_code",
		"implicit",
		"refresh_token"
	],
	"is_first_party": true,
	"is_token_endpoint_ip_header_trusted": false,
	"jwt_configuration": {
		"alg": "RS256",
		"lifetime_in_seconds": 36000,
		"secret_encoded": false
	},
	"logo_uri": "https://myapp.com/logo.png",
	"name": "My SPA",
	"oidc_conformant": true,
	"sso": true,
	"sso_disabled": false,
	"tenant": "##AUTH0_TENANT_NAME##",
	"token_endpoint_auth_method": "none",
	"web_origins": [
		"https://##ENV##.myapp.com"
	]
}
